{
  "x.com": {
    "domain": "x.com",
    "best_strategy": null,
    "best_result": null,
    "all_results": [
      {
        "strategy_name": "fake_simple",
        "domain": "x.com",
        "success": false,
        "latency_ms": 0,
        "data_transferred": 0,
        "connection_duration": 0,
        "error": "'utf-8' codec can't decode byte 0xd2 in position 4: invalid continuation byte",
        "score": 0.0
      },
      {
        "strategy_name": "fake_simple+low_ttl_fake",
        "domain": "x.com",
        "success": false,
        "latency_ms": 0,
        "data_transferred": 0,
        "connection_duration": 0,
        "error": "'utf-8' codec can't decode byte 0xd2 in position 4: invalid continuation byte",
        "score": 0.0
      },
      {
        "strategy_name": "ip_fragmentation",
        "domain": "x.com",
        "success": false,
        "latency_ms": 0,
        "data_transferred": 0,
        "connection_duration": 0,
        "error": "'utf-8' codec can't decode byte 0xd2 in position 4: invalid continuation byte",
        "score": 0.0
      },
      {
        "strategy_name": "split_advanced+multisplit_basic",
        "domain": "x.com",
        "success": false,
        "latency_ms": 0,
        "data_transferred": 0,
        "connection_duration": 0,
        "error": "'utf-8' codec can't decode byte 0xd2 in position 4: invalid continuation byte",
        "score": 0.0
      },
      {
        "strategy_name": "fake_simple+split_basic+split_advanced",
        "domain": "x.com",
        "success": false,
        "latency_ms": 0,
        "data_transferred": 0,
        "connection_duration": 0,
        "error": "'utf-8' codec can't decode byte 0xd2 in position 4: invalid continuation byte",
        "score": 0.0
      },
      {
        "strategy_name": "disorder_simple+stealth_bypass",
        "domain": "x.com",
        "success": false,
        "latency_ms": 0,
        "data_transferred": 0,
        "connection_duration": 0,
        "error": "'utf-8' codec can't decode byte 0xd2 in position 4: invalid continuation byte",
        "score": 0.0
      },
      {
        "strategy_name": "fake_simple+fake_advanced+low_ttl_fake",
        "domain": "x.com",
        "success": false,
        "latency_ms": 0,
        "data_transferred": 0,
        "connection_duration": 0,
        "error": "'utf-8' codec can't decode byte 0xd2 in position 4: invalid continuation byte",
        "score": 0.0
      },
      {
        "strategy_name": "fake_advanced+disorder_simple+split_advanced",
        "domain": "x.com",
        "success": false,
        "latency_ms": 0,
        "data_transferred": 0,
        "connection_duration": 0,
        "error": "'utf-8' codec can't decode byte 0xd2 in position 4: invalid continuation byte",
        "score": 0.0
      },
      {
        "strategy_name": "disorder_simple+split_advanced+high_ttl_disorder",
        "domain": "x.com",
        "success": false,
        "latency_ms": 0,
        "data_transferred": 0,
        "connection_duration": 0,
        "error": "'utf-8' codec can't decode byte 0xd2 in position 4: invalid continuation byte",
        "score": 0.0
      },
      {
        "strategy_name": "split_basic+low_ttl_fake+medium_ttl_split",
        "domain": "x.com",
        "success": false,
        "latency_ms": 0,
        "data_transferred": 0,
        "connection_duration": 0,
        "error": "'utf-8' codec can't decode byte 0xd2 in position 4: invalid continuation byte",
        "score": 0.0
      }
    ],
    "success_rate": 0.0,
    "zapret_string": null
  },
  "instagram.com": {
    "domain": "instagram.com",
    "best_strategy": null,
    "best_result": null,
    "all_results": [
      {
        "strategy_name": "fake_simple",
        "domain": "instagram.com",
        "success": false,
        "latency_ms": 0,
        "data_transferred": 0,
        "connection_duration": 0,
        "error": "'utf-8' codec can't decode byte 0xd2 in position 4: invalid continuation byte",
        "score": 0.0
      },
      {
        "strategy_name": "fake_simple+low_ttl_fake",
        "domain": "instagram.com",
        "success": false,
        "latency_ms": 0,
        "data_transferred": 0,
        "connection_duration": 0,
        "error": "'utf-8' codec can't decode byte 0xd2 in position 4: invalid continuation byte",
        "score": 0.0
      },
      {
        "strategy_name": "ip_fragmentation",
        "domain": "instagram.com",
        "success": false,
        "latency_ms": 0,
        "data_transferred": 0,
        "connection_duration": 0,
        "error": "'utf-8' codec can't decode byte 0xd2 in position 4: invalid continuation byte",
        "score": 0.0
      },
      {
        "strategy_name": "split_advanced+multisplit_basic",
        "domain": "instagram.com",
        "success": false,
        "latency_ms": 0,
        "data_transferred": 0,
        "connection_duration": 0,
        "error": "'utf-8' codec can't decode byte 0xd2 in position 4: invalid continuation byte",
        "score": 0.0
      },
      {
        "strategy_name": "fake_simple+split_basic+split_advanced",
        "domain": "instagram.com",
        "success": false,
        "latency_ms": 0,
        "data_transferred": 0,
        "connection_duration": 0,
        "error": "'utf-8' codec can't decode byte 0xd2 in position 4: invalid continuation byte",
        "score": 0.0
      },
      {
        "strategy_name": "disorder_simple+stealth_bypass",
        "domain": "instagram.com",
        "success": false,
        "latency_ms": 0,
        "data_transferred": 0,
        "connection_duration": 0,
        "error": "'utf-8' codec can't decode byte 0xd2 in position 4: invalid continuation byte",
        "score": 0.0
      },
      {
        "strategy_name": "fake_simple+fake_advanced+low_ttl_fake",
        "domain": "instagram.com",
        "success": false,
        "latency_ms": 0,
        "data_transferred": 0,
        "connection_duration": 0,
        "error": "'utf-8' codec can't decode byte 0xd2 in position 4: invalid continuation byte",
        "score": 0.0
      },
      {
        "strategy_name": "fake_advanced+disorder_simple+split_advanced",
        "domain": "instagram.com",
        "success": false,
        "latency_ms": 0,
        "data_transferred": 0,
        "connection_duration": 0,
        "error": "'utf-8' codec can't decode byte 0xd2 in position 4: invalid continuation byte",
        "score": 0.0
      },
      {
        "strategy_name": "disorder_simple+split_advanced+high_ttl_disorder",
        "domain": "instagram.com",
        "success": false,
        "latency_ms": 0,
        "data_transferred": 0,
        "connection_duration": 0,
        "error": "'utf-8' codec can't decode byte 0xd2 in position 4: invalid continuation byte",
        "score": 0.0
      },
      {
        "strategy_name": "split_basic+low_ttl_fake+medium_ttl_split",
        "domain": "instagram.com",
        "success": false,
        "latency_ms": 0,
        "data_transferred": 0,
        "connection_duration": 0,
        "error": "'utf-8' codec can't decode byte 0xd2 in position 4: invalid continuation byte",
        "score": 0.0
      }
    ],
    "success_rate": 0.0,
    "zapret_string": null
  },
  "rutracker.org": {
    "domain": "rutracker.org",
    "best_strategy": null,
    "best_result": null,
    "all_results": [
      {
        "strategy_name": "fake_simple",
        "domain": "rutracker.org",
        "success": false,
        "latency_ms": 0,
        "data_transferred": 0,
        "connection_duration": 0,
        "error": "'utf-8' codec can't decode byte 0xd2 in position 4: invalid continuation byte",
        "score": 0.0
      },
      {
        "strategy_name": "fake_simple+low_ttl_fake",
        "domain": "rutracker.org",
        "success": false,
        "latency_ms": 0,
        "data_transferred": 0,
        "connection_duration": 0,
        "error": "'utf-8' codec can't decode byte 0xd2 in position 4: invalid continuation byte",
        "score": 0.0
      },
      {
        "strategy_name": "ip_fragmentation",
        "domain": "rutracker.org",
        "success": false,
        "latency_ms": 0,
        "data_transferred": 0,
        "connection_duration": 0,
        "error": "'utf-8' codec can't decode byte 0xd2 in position 4: invalid continuation byte",
        "score": 0.0
      },
      {
        "strategy_name": "split_advanced+multisplit_basic",
        "domain": "rutracker.org",
        "success": false,
        "latency_ms": 0,
        "data_transferred": 0,
        "connection_duration": 0,
        "error": "'utf-8' codec can't decode byte 0xd2 in position 4: invalid continuation byte",
        "score": 0.0
      },
      {
        "strategy_name": "fake_simple+split_basic+split_advanced",
        "domain": "rutracker.org",
        "success": false,
        "latency_ms": 0,
        "data_transferred": 0,
        "connection_duration": 0,
        "error": "'utf-8' codec can't decode byte 0xd2 in position 4: invalid continuation byte",
        "score": 0.0
      },
      {
        "strategy_name": "disorder_simple+stealth_bypass",
        "domain": "rutracker.org",
        "success": false,
        "latency_ms": 0,
        "data_transferred": 0,
        "connection_duration": 0,
        "error": "'utf-8' codec can't decode byte 0xd2 in position 4: invalid continuation byte",
        "score": 0.0
      },
      {
        "strategy_name": "fake_simple+fake_advanced+low_ttl_fake",
        "domain": "rutracker.org",
        "success": false,
        "latency_ms": 0,
        "data_transferred": 0,
        "connection_duration": 0,
        "error": "'utf-8' codec can't decode byte 0xd2 in position 4: invalid continuation byte",
        "score": 0.0
      },
      {
        "strategy_name": "fake_advanced+disorder_simple+split_advanced",
        "domain": "rutracker.org",
        "success": false,
        "latency_ms": 0,
        "data_transferred": 0,
        "connection_duration": 0,
        "error": "'utf-8' codec can't decode byte 0xd2 in position 4: invalid continuation byte",
        "score": 0.0
      },
      {
        "strategy_name": "disorder_simple+split_advanced+high_ttl_disorder",
        "domain": "rutracker.org",
        "success": false,
        "latency_ms": 0,
        "data_transferred": 0,
        "connection_duration": 0,
        "error": "'utf-8' codec can't decode byte 0xd2 in position 4: invalid continuation byte",
        "score": 0.0
      },
      {
        "strategy_name": "split_basic+low_ttl_fake+medium_ttl_split",
        "domain": "rutracker.org",
        "success": false,
        "latency_ms": 0,
        "data_transferred": 0,
        "connection_duration": 0,
        "error": "'utf-8' codec can't decode byte 0xd2 in position 4: invalid continuation byte",
        "score": 0.0
      }
    ],
    "success_rate": 0.0,
    "zapret_string": null
  }
}